LICENSE
README.md
setup.cfg
setup.py
permacache/__init__.py
permacache/cache.py
permacache/cache_miss_error.py
permacache/dict_function.py
permacache/hash.py
permacache/locked_shelf.py
permacache/main.py
permacache/no_cache.py
permacache/out_file_cache.py
permacache/swap_unpickler.py
permacache/utils.py
permacache.egg-info/PKG-INFO
permacache.egg-info/SOURCES.txt
permacache.egg-info/dependency_links.txt
permacache.egg-info/entry_points.txt
permacache.egg-info/requires.txt
permacache.egg-info/top_level.txt
tests/__init__.py
tests/dict_function_test.py
tests/locked_shelf_test.py
tests/parallel_access_locked_shelf_test.py
tests/stringify_test.py
tests/test_cache.py
tests/test_count.py
tests/test_export.py
tests/test_out_file_cache.py
tests/test_parallel_cache.py
tests/test_module/__init__.py
tests/test_module/a.py
tests/test_module/b.py
tests/test_module/c.py