Metadata-Version: 2.4
Name: permacache
Version: 4.3.1
Summary: Permanant cache.
Home-page: https://github.com/kavigupta/permacache
Author: Kavi Gupta
Author-email: permacache@kavigupta.org
Classifier: Programming Language :: Python :: 3.8
Classifier: Programming Language :: Python :: 3.9
Classifier: Programming Language :: Python :: 3.10
Classifier: Programming Language :: Python :: 3.11
Classifier: Programming Language :: Python :: 3.12
Classifier: Operating System :: OS Independent
Requires-Python: >=3.6
License-File: LICENSE
Requires-Dist: filelock>=3.0.12
Requires-Dist: appdirs>=1.4.4
Dynamic: author
Dynamic: author-email
Dynamic: classifier
Dynamic: description
Dynamic: description-content-type
Dynamic: home-page
Dynamic: license-file
Dynamic: requires-dist
Dynamic: requires-python
Dynamic: summary
